{"nodes": [{"id": "app_tabs_layout_tsx", "label": "_layout.tsx", "file_type": "code", "source_file": "app/(tabs)/_layout.tsx", "source_location": "L1"}, {"id": "layout_tabicon", "label": "TabIcon()", "file_type": "code", "source_file": "app/(tabs)/_layout.tsx", "source_location": "L11"}], "edges": [{"source": "app_tabs_layout_tsx", "target": "react", "relation": "imports_from", "confidence": "EXTRACTED", "source_file": "app/(tabs)/_layout.tsx", "source_location": "L1", "weight": 1.0}, {"source": "app_tabs_layout_tsx", "target": "expo_router", "relation": "imports_from", "confidence": "EXTRACTED", "source_file": "app/(tabs)/_layout.tsx", "source_location": "L2", "weight": 1.0}, {"source": "app_tabs_layout_tsx", "target": "react_native", "relation": "imports_from", "confidence": "EXTRACTED", "source_file": "app/(tabs)/_layout.tsx", "source_location": "L3", "weight": 1.0}, {"source": "app_tabs_layout_tsx", "target": "react_i18next", "relation": "imports_from", "confidence": "EXTRACTED", "source_file": "app/(tabs)/_layout.tsx", "source_location": "L4", "weight": 1.0}, {"source": "app_tabs_layout_tsx", "target": "vector_icons", "relation": "imports_from", "confidence": "EXTRACTED", "source_file": "app/(tabs)/_layout.tsx", "source_location": "L5", "weight": 1.0}, {"source": "app_tabs_layout_tsx", "target": "app_tabs_src_components_addsubscriptionsheet", "relation": "imports_from", "confidence": "EXTRACTED", "source_file": "app/(tabs)/_layout.tsx", "source_location": "L6", "weight": 1.0}, {"source": "app_tabs_layout_tsx", "target": "app_tabs_src_constants", "relation": "imports_from", "confidence": "EXTRACTED", "source_file": "app/(tabs)/_layout.tsx", "source_location": "L7", "weight": 1.0}, {"source": "app_tabs_layout_tsx", "target": "app_tabs_src_theme", "relation": "imports_from", "confidence": "EXTRACTED", "source_file": "app/(tabs)/_layout.tsx", "source_location": "L8", "weight": 1.0}, {"source": "app_tabs_layout_tsx", "target": "app_tabs_src_stores_uistore", "relation": "imports_from", "confidence": "EXTRACTED", "source_file": "app/(tabs)/_layout.tsx", "source_location": "L9", "weight": 1.0}, {"source": "app_tabs_layout_tsx", "target": "layout_tabicon", "relation": "contains", "confidence": "EXTRACTED", "source_file": "app/(tabs)/_layout.tsx", "source_location": "L11", "weight": 1.0}], "raw_calls": [{"caller_nid": "layout_tabicon", "callee": "useTheme", "source_file": "app/(tabs)/_layout.tsx", "source_location": "L12"}]}